{
  "users": [
    {
      "id": 1,
      "username": "admin",
      "email": "admin123@gmail.com",
      "password": "admin123",
      "img": "",
      "posts": 0
    },
    {
      "username": "RustyTractor",
      "email": "urbanotto999@gmail.com",
      "password": "Menomano99",
      "img": "",
      "posts": 3,
      "id": 2
    }
  ],
  "post": [
    {
      "userId": 2,
      "title": "What are Promises ?",
      "text": "Maybe a bot question , but i dont understend what are the Promises... :(",
      "comments": 0,
      "date": "2022-09-18T13:26:07.876Z",
      "id": 1
    }
  ],
  "comment": [
    {
      "id": 1,
      "postId": 1,
      "userId": 2,
      "author": "József!",
      "text": "Random Comment text",
      "likes": 0,
      "dislikes": 0
    }
  ]
}
